MANIFEST.in
README.md
pyproject.toml
setup.py
amuse_phigrape.egg-info/PKG-INFO
amuse_phigrape.egg-info/SOURCES.txt
amuse_phigrape.egg-info/dependency_links.txt
amuse_phigrape.egg-info/requires.txt
amuse_phigrape.egg-info/top_level.txt
src/amuse/community/phigrape/.stop
src/amuse/community/phigrape/Makefile
src/amuse/community/phigrape/QUICKSTART.readme
src/amuse/community/phigrape/__init__.py
src/amuse/community/phigrape/_version.py
src/amuse/community/phigrape/interface.F
src/amuse/community/phigrape/interface.py
src/amuse/community/phigrape/phiGRAPE.readme
src/amuse/community/phigrape/sapporo.config
src/amuse/community/phigrape/src/Makefile
src/amuse/community/phigrape/src/allgather_ap.F
src/amuse/community/phigrape/src/cmcorr.F
src/amuse/community/phigrape/src/corrector.F
src/amuse/community/phigrape/src/cputime.F
src/amuse/community/phigrape/src/energy.F
src/amuse/community/phigrape/src/fthread.f
src/amuse/community/phigrape/src/general.inc
src/amuse/community/phigrape/src/get_min_t.F
src/amuse/community/phigrape/src/gravity.F
src/amuse/community/phigrape/src/initgrape.F
src/amuse/community/phigrape/src/initmpi.F
src/amuse/community/phigrape/src/initpars.F
src/amuse/community/phigrape/src/main.F
src/amuse/community/phigrape/src/mpi.inc
src/amuse/community/phigrape/src/output.F
src/amuse/community/phigrape/src/paras.inc
src/amuse/community/phigrape/src/predict_potential.F
src/amuse/community/phigrape/src/predictor.F
src/amuse/community/phigrape/src/pt.c
src/amuse/community/phigrape/src/pt.h
src/amuse/community/phigrape/src/ptf77.c
src/amuse/community/phigrape/src/readbodydata.F
src/amuse/community/phigrape/src/readpars.F
src/amuse/community/phigrape/src/readrestartfile.F
src/amuse/community/phigrape/src/selectactive.F
src/amuse/community/phigrape/src/selectsync.F
src/amuse/community/phigrape/src/sendbodies2grape.F
src/amuse/community/phigrape/src/sendbodydata.F
src/amuse/community/phigrape/src/sendinpdata.F
src/amuse/community/phigrape/src/start_viewer.F
src/amuse/community/phigrape/src/sumforces.F
src/amuse/community/phigrape/src/sync.F
src/amuse/community/phigrape/src/timestep.F
src/amuse/community/phigrape/src/update_grape.F
